{
    "annotations": {
      "list": [
        {
          "builtIn": 1,
          "datasource": {
            "type": "grafana",
            "uid": "-- Grafana --"
          },
          "enable": true,
          "hide": true,
          "iconColor": "rgba(0, 211, 255, 1)",
          "name": "Annotations & Alerts",
          "type": "dashboard"
        }
      ]
    },
    "editable": true,
    "fiscalYearStartMonth": 0,
    "graphTooltip": 0,
    "id": 14,
    "links": [],
    "panels": [
      {
        "datasource": {
          "type": "prometheus",
          "uid": "grafanacloud-prom"
        },
        "fieldConfig": {
          "defaults": {
            "color": {
              "mode": "palette-classic"
            },
            "custom": {
              "axisBorderShow": false,
              "axisCenteredZero": false,
              "axisColorMode": "text",
              "axisLabel": "",
              "axisPlacement": "auto",
              "barAlignment": 0,
              "barWidthFactor": 0.6,
              "drawStyle": "line",
              "fillOpacity": 0,
              "gradientMode": "none",
              "hideFrom": {
                "legend": false,
                "tooltip": false,
                "viz": false
              },
              "insertNulls": false,
              "lineInterpolation": "linear",
              "lineWidth": 1,
              "pointSize": 5,
              "scaleDistribution": {
                "type": "linear"
              },
              "showPoints": "auto",
              "spanNulls": false,
              "stacking": {
                "group": "A",
                "mode": "none"
              },
              "thresholdsStyle": {
                "mode": "off"
              }
            },
            "displayName": "active_users",
            "mappings": [],
            "thresholds": {
              "mode": "absolute",
              "steps": [
                {
                  "color": "green"
                },
                {
                  "color": "red",
                  "value": 80
                }
              ]
            }
          },
          "overrides": []
        },
        "gridPos": {
          "h": 8,
          "w": 6,
          "x": 0,
          "y": 0
        },
        "id": 6,
        "options": {
          "legend": {
            "calcs": [],
            "displayMode": "list",
            "placement": "bottom",
            "showLegend": true
          },
          "tooltip": {
            "hideZeros": false,
            "mode": "single",
            "sort": "none"
          }
        },
        "pluginVersion": "11.6.0-84491.patch1-84812",
        "targets": [
          {
            "disableTextWrap": false,
            "editorMode": "builder",
            "expr": "active_users_total",
            "fullMetaSearch": false,
            "includeNullMetadata": true,
            "legendFormat": "__auto",
            "range": true,
            "refId": "A",
            "useBackend": false
          }
        ],
        "title": "Active users",
        "type": "timeseries"
      },
      {
        "datasource": {
          "type": "prometheus",
          "uid": "grafanacloud-prom"
        },
        "fieldConfig": {
          "defaults": {
            "color": {
              "mode": "palette-classic"
            },
            "custom": {
              "axisBorderShow": false,
              "axisCenteredZero": false,
              "axisColorMode": "text",
              "axisLabel": "",
              "axisPlacement": "auto",
              "barAlignment": 0,
              "barWidthFactor": 0.6,
              "drawStyle": "line",
              "fillOpacity": 0,
              "gradientMode": "none",
              "hideFrom": {
                "legend": false,
                "tooltip": false,
                "viz": false
              },
              "insertNulls": false,
              "lineInterpolation": "linear",
              "lineWidth": 1,
              "pointSize": 5,
              "scaleDistribution": {
                "type": "linear"
              },
              "showPoints": "auto",
              "spanNulls": false,
              "stacking": {
                "group": "A",
                "mode": "none"
              },
              "thresholdsStyle": {
                "mode": "off"
              }
            },
            "mappings": [],
            "thresholds": {
              "mode": "absolute",
              "steps": [
                {
                  "color": "green"
                },
                {
                  "color": "red",
                  "value": 80
                }
              ]
            }
          },
          "overrides": [
            {
              "matcher": {
                "id": "byName",
                "options": "auth_success_total"
              },
              "properties": [
                {
                  "id": "displayName",
                  "value": "success"
                }
              ]
            },
            {
              "matcher": {
                "id": "byName",
                "options": "auth_fail_total"
              },
              "properties": [
                {
                  "id": "displayName",
                  "value": "failure"
                }
              ]
            }
          ]
        },
        "gridPos": {
          "h": 8,
          "w": 6,
          "x": 6,
          "y": 0
        },
        "id": 7,
        "options": {
          "legend": {
            "calcs": [],
            "displayMode": "list",
            "placement": "bottom",
            "showLegend": true
          },
          "tooltip": {
            "hideZeros": false,
            "mode": "single",
            "sort": "none"
          }
        },
        "pluginVersion": "11.6.0-84491.patch1-84812",
        "targets": [
          {
            "disableTextWrap": false,
            "editorMode": "builder",
            "expr": "auth_success_total",
            "fullMetaSearch": false,
            "includeNullMetadata": true,
            "legendFormat": "__auto",
            "range": true,
            "refId": "A",
            "useBackend": false
          },
          {
            "datasource": {
              "type": "prometheus",
              "uid": "grafanacloud-prom"
            },
            "disableTextWrap": false,
            "editorMode": "builder",
            "expr": "auth_fail_total",
            "fullMetaSearch": false,
            "hide": false,
            "includeNullMetadata": true,
            "instant": false,
            "legendFormat": "__auto",
            "range": true,
            "refId": "B",
            "useBackend": false
          }
        ],
        "title": "Authentications",
        "type": "timeseries"
      },
      {
        "datasource": {
          "type": "prometheus",
          "uid": "grafanacloud-prom"
        },
        "fieldConfig": {
          "defaults": {
            "color": {
              "mode": "palette-classic"
            },
            "custom": {
              "axisBorderShow": false,
              "axisCenteredZero": false,
              "axisColorMode": "text",
              "axisLabel": "",
              "axisPlacement": "auto",
              "barAlignment": 0,
              "barWidthFactor": 0.6,
              "drawStyle": "line",
              "fillOpacity": 0,
              "gradientMode": "none",
              "hideFrom": {
                "legend": false,
                "tooltip": false,
                "viz": false
              },
              "insertNulls": false,
              "lineInterpolation": "linear",
              "lineWidth": 1,
              "pointSize": 5,
              "scaleDistribution": {
                "type": "linear"
              },
              "showPoints": "auto",
              "spanNulls": false,
              "stacking": {
                "group": "A",
                "mode": "none"
              },
              "thresholdsStyle": {
                "mode": "off"
              }
            },
            "mappings": [],
            "thresholds": {
              "mode": "absolute",
              "steps": [
                {
                  "color": "green"
                },
                {
                  "color": "red",
                  "value": 80
                }
              ]
            }
          },
          "overrides": [
            {
              "matcher": {
                "id": "byName",
                "options": "{__name__=\"requests_total\"}"
              },
              "properties": [
                {
                  "id": "displayName",
                  "value": "all"
                }
              ]
            },
            {
              "matcher": {
                "id": "byName",
                "options": "{__name__=\"requests_GET_total\", method=\"GET\"}"
              },
              "properties": [
                {
                  "id": "displayName",
                  "value": "GET"
                }
              ]
            },
            {
              "matcher": {
                "id": "byName",
                "options": "{__name__=\"requests_PUT_total\", method=\"PUT\"}"
              },
              "properties": [
                {
                  "id": "displayName",
                  "value": "PUT"
                }
              ]
            },
            {
              "matcher": {
                "id": "byName",
                "options": "{__name__=\"requests_POST_total\", method=\"POST\"}"
              },
              "properties": [
                {
                  "id": "displayName",
                  "value": "POST"
                }
              ]
            },
            {
              "matcher": {
                "id": "byName",
                "options": "{__name__=\"requests_DELETE_total\", method=\"DELETE\"}"
              },
              "properties": [
                {
                  "id": "displayName",
                  "value": "DELETE"
                }
              ]
            }
          ]
        },
        "gridPos": {
          "h": 8,
          "w": 12,
          "x": 12,
          "y": 0
        },
        "id": 5,
        "interval": "60",
        "options": {
          "legend": {
            "calcs": [],
            "displayMode": "list",
            "placement": "bottom",
            "showLegend": true
          },
          "tooltip": {
            "hideZeros": false,
            "mode": "single",
            "sort": "none"
          }
        },
        "pluginVersion": "11.6.0-84491.patch1-84812",
        "targets": [
          {
            "disableTextWrap": false,
            "editorMode": "builder",
            "expr": "requests_total",
            "fullMetaSearch": false,
            "includeNullMetadata": true,
            "legendFormat": "__auto",
            "range": true,
            "refId": "A",
            "useBackend": false
          },
          {
            "datasource": {
              "type": "prometheus",
              "uid": "grafanacloud-prom"
            },
            "disableTextWrap": false,
            "editorMode": "builder",
            "expr": "requests_GET_total",
            "fullMetaSearch": false,
            "hide": false,
            "includeNullMetadata": true,
            "instant": false,
            "legendFormat": "__auto",
            "range": true,
            "refId": "B",
            "useBackend": false
          },
          {
            "datasource": {
              "type": "prometheus",
              "uid": "grafanacloud-prom"
            },
            "disableTextWrap": false,
            "editorMode": "builder",
            "expr": "requests_PUT_total",
            "fullMetaSearch": false,
            "hide": false,
            "includeNullMetadata": true,
            "instant": false,
            "legendFormat": "__auto",
            "range": true,
            "refId": "C",
            "useBackend": false
          },
          {
            "datasource": {
              "type": "prometheus",
              "uid": "grafanacloud-prom"
            },
            "disableTextWrap": false,
            "editorMode": "builder",
            "expr": "requests_POST_total",
            "fullMetaSearch": false,
            "hide": false,
            "includeNullMetadata": true,
            "instant": false,
            "legendFormat": "__auto",
            "range": true,
            "refId": "D",
            "useBackend": false
          },
          {
            "datasource": {
              "type": "prometheus",
              "uid": "grafanacloud-prom"
            },
            "disableTextWrap": false,
            "editorMode": "builder",
            "expr": "requests_DELETE_total",
            "fullMetaSearch": false,
            "hide": false,
            "includeNullMetadata": true,
            "instant": false,
            "legendFormat": "__auto",
            "range": true,
            "refId": "E",
            "useBackend": false
          }
        ],
        "title": "HTTP requests/minute",
        "type": "timeseries"
      },
      {
        "datasource": {
          "type": "prometheus",
          "uid": "grafanacloud-prom"
        },
        "fieldConfig": {
          "defaults": {
            "color": {
              "mode": "thresholds"
            },
            "mappings": [],
            "thresholds": {
              "mode": "absolute",
              "steps": [
                {
                  "color": "green"
                },
                {
                  "color": "red",
                  "value": 80
                }
              ]
            }
          },
          "overrides": [
            {
              "matcher": {
                "id": "byName",
                "options": "cpu_percent"
              },
              "properties": [
                {
                  "id": "displayName",
                  "value": "CPU"
                }
              ]
            },
            {
              "matcher": {
                "id": "byName",
                "options": "memory_percent"
              },
              "properties": [
                {
                  "id": "displayName",
                  "value": "Memory"
                }
              ]
            }
          ]
        },
        "gridPos": {
          "h": 8,
          "w": 12,
          "x": 0,
          "y": 8
        },
        "id": 8,
        "options": {
          "minVizHeight": 75,
          "minVizWidth": 75,
          "orientation": "auto",
          "reduceOptions": {
            "calcs": [
              "lastNotNull"
            ],
            "fields": "",
            "values": false
          },
          "showThresholdLabels": false,
          "showThresholdMarkers": true,
          "sizing": "auto"
        },
        "pluginVersion": "11.6.0-84491.patch1-84812",
        "targets": [
          {
            "datasource": {
              "type": "prometheus",
              "uid": "grafanacloud-prom"
            },
            "disableTextWrap": false,
            "editorMode": "builder",
            "expr": "memory_percent",
            "fullMetaSearch": false,
            "hide": false,
            "includeNullMetadata": true,
            "instant": false,
            "legendFormat": "__auto",
            "range": true,
            "refId": "B",
            "useBackend": false
          },
          {
            "disableTextWrap": false,
            "editorMode": "code",
            "expr": "cpu_percent",
            "fullMetaSearch": false,
            "includeNullMetadata": true,
            "legendFormat": "__auto",
            "range": true,
            "refId": "A",
            "useBackend": false
          }
        ],
        "title": "CPU and memory usage",
        "type": "gauge"
      },
      {
        "datasource": {
          "type": "prometheus",
          "uid": "grafanacloud-prom"
        },
        "fieldConfig": {
          "defaults": {
            "color": {
              "mode": "thresholds"
            },
            "custom": {
              "axisBorderShow": false,
              "axisCenteredZero": false,
              "axisColorMode": "text",
              "axisLabel": "",
              "axisPlacement": "auto",
              "barAlignment": 0,
              "barWidthFactor": 0.6,
              "drawStyle": "line",
              "fillOpacity": 0,
              "gradientMode": "none",
              "hideFrom": {
                "legend": false,
                "tooltip": false,
                "viz": false
              },
              "insertNulls": false,
              "lineInterpolation": "smooth",
              "lineStyle": {
                "fill": "solid"
              },
              "lineWidth": 1,
              "pointSize": 5,
              "scaleDistribution": {
                "type": "linear"
              },
              "showPoints": "auto",
              "spanNulls": false,
              "stacking": {
                "group": "A",
                "mode": "none"
              },
              "thresholdsStyle": {
                "mode": "off"
              }
            },
            "displayName": "Request latency",
            "mappings": [],
            "thresholds": {
              "mode": "absolute",
              "steps": [
                {
                  "color": "green"
                },
                {
                  "color": "red",
                  "value": 80
                }
              ]
            },
            "unit": "ms"
          },
          "overrides": []
        },
        "gridPos": {
          "h": 8,
          "w": 12,
          "x": 12,
          "y": 8
        },
        "id": 11,
        "options": {
          "legend": {
            "calcs": [],
            "displayMode": "list",
            "placement": "bottom",
            "showLegend": true
          },
          "tooltip": {
            "hideZeros": false,
            "mode": "single",
            "sort": "none"
          }
        },
        "pluginVersion": "11.6.0-84491.patch1-84812",
        "targets": [
          {
            "disableTextWrap": false,
            "editorMode": "builder",
            "expr": "service_latency_ratio",
            "fullMetaSearch": false,
            "includeNullMetadata": true,
            "legendFormat": "__auto",
            "range": true,
            "refId": "A",
            "useBackend": false
          }
        ],
        "title": "Request Latency",
        "type": "timeseries"
      },
      {
        "datasource": {
          "type": "prometheus",
          "uid": "grafanacloud-prom"
        },
        "fieldConfig": {
          "defaults": {
            "color": {
              "mode": "palette-classic"
            },
            "custom": {
              "axisBorderShow": false,
              "axisCenteredZero": false,
              "axisColorMode": "text",
              "axisLabel": "",
              "axisPlacement": "auto",
              "barAlignment": 0,
              "barWidthFactor": 0.6,
              "drawStyle": "line",
              "fillOpacity": 0,
              "gradientMode": "none",
              "hideFrom": {
                "legend": false,
                "tooltip": false,
                "viz": false
              },
              "insertNulls": false,
              "lineInterpolation": "linear",
              "lineWidth": 1,
              "pointSize": 5,
              "scaleDistribution": {
                "type": "linear"
              },
              "showPoints": "auto",
              "spanNulls": false,
              "stacking": {
                "group": "A",
                "mode": "none"
              },
              "thresholdsStyle": {
                "mode": "off"
              }
            },
            "mappings": [],
            "thresholds": {
              "mode": "absolute",
              "steps": [
                {
                  "color": "green"
                },
                {
                  "color": "red",
                  "value": 80
                }
              ]
            }
          },
          "overrides": [
            {
              "matcher": {
                "id": "byName",
                "options": "pizza_success_total"
              },
              "properties": [
                {
                  "id": "displayName",
                  "value": "Pizza purchases"
                }
              ]
            },
            {
              "matcher": {
                "id": "byName",
                "options": "pizza_failure_total"
              },
              "properties": [
                {
                  "id": "displayName",
                  "value": "Purchase failures"
                }
              ]
            }
          ]
        },
        "gridPos": {
          "h": 8,
          "w": 6,
          "x": 0,
          "y": 16
        },
        "id": 9,
        "options": {
          "legend": {
            "calcs": [],
            "displayMode": "list",
            "placement": "bottom",
            "showLegend": true
          },
          "tooltip": {
            "hideZeros": false,
            "mode": "single",
            "sort": "none"
          }
        },
        "pluginVersion": "11.6.0-84491.patch1-84812",
        "targets": [
          {
            "disableTextWrap": false,
            "editorMode": "builder",
            "expr": "pizza_success_total",
            "fullMetaSearch": false,
            "includeNullMetadata": true,
            "legendFormat": "__auto",
            "range": true,
            "refId": "A",
            "useBackend": false
          },
          {
            "datasource": {
              "type": "prometheus",
              "uid": "grafanacloud-prom"
            },
            "disableTextWrap": false,
            "editorMode": "builder",
            "expr": "pizza_failure_total",
            "fullMetaSearch": false,
            "hide": false,
            "includeNullMetadata": true,
            "instant": false,
            "legendFormat": "__auto",
            "range": true,
            "refId": "B",
            "useBackend": false
          }
        ],
        "title": "Pizza Purchases",
        "type": "timeseries"
      },
      {
        "datasource": {
          "type": "prometheus",
          "uid": "grafanacloud-prom"
        },
        "fieldConfig": {
          "defaults": {
            "color": {
              "mode": "thresholds"
            },
            "mappings": [],
            "thresholds": {
              "mode": "absolute",
              "steps": [
                {
                  "color": "green"
                },
                {
                  "color": "red",
                  "value": 80
                }
              ]
            },
            "unit": "currencyBTC"
          },
          "overrides": []
        },
        "gridPos": {
          "h": 8,
          "w": 6,
          "x": 6,
          "y": 16
        },
        "id": 10,
        "options": {
          "displayMode": "gradient",
          "legend": {
            "calcs": [],
            "displayMode": "list",
            "placement": "bottom",
            "showLegend": false
          },
          "maxVizHeight": 300,
          "minVizHeight": 16,
          "minVizWidth": 8,
          "namePlacement": "auto",
          "orientation": "vertical",
          "reduceOptions": {
            "calcs": [
              "lastNotNull"
            ],
            "fields": "",
            "values": false
          },
          "showUnfilled": true,
          "sizing": "auto",
          "text": {
            "valueSize": 100
          },
          "valueMode": "color"
        },
        "pluginVersion": "11.6.0-84491.patch1-84812",
        "targets": [
          {
            "disableTextWrap": false,
            "editorMode": "builder",
            "expr": "pizza_revenue_total",
            "fullMetaSearch": false,
            "includeNullMetadata": true,
            "legendFormat": "__auto",
            "range": true,
            "refId": "A",
            "useBackend": false
          }
        ],
        "title": "Revenue",
        "type": "bargauge"
      },
      {
        "datasource": {
          "type": "prometheus",
          "uid": "grafanacloud-prom"
        },
        "fieldConfig": {
          "defaults": {
            "color": {
              "mode": "palette-classic"
            },
            "custom": {
              "axisBorderShow": false,
              "axisCenteredZero": false,
              "axisColorMode": "text",
              "axisLabel": "",
              "axisPlacement": "auto",
              "barAlignment": 0,
              "barWidthFactor": 0.6,
              "drawStyle": "line",
              "fillOpacity": 0,
              "gradientMode": "none",
              "hideFrom": {
                "legend": false,
                "tooltip": false,
                "viz": false
              },
              "insertNulls": false,
              "lineInterpolation": "linear",
              "lineWidth": 1,
              "pointSize": 5,
              "scaleDistribution": {
                "type": "linear"
              },
              "showPoints": "auto",
              "spanNulls": false,
              "stacking": {
                "group": "A",
                "mode": "none"
              },
              "thresholdsStyle": {
                "mode": "off"
              }
            },
            "displayName": "Pizza latency",
            "mappings": [],
            "thresholds": {
              "mode": "absolute",
              "steps": [
                {
                  "color": "green"
                },
                {
                  "color": "red",
                  "value": 80
                }
              ]
            }
          },
          "overrides": []
        },
        "gridPos": {
          "h": 8,
          "w": 12,
          "x": 12,
          "y": 16
        },
        "id": 12,
        "options": {
          "legend": {
            "calcs": [],
            "displayMode": "list",
            "placement": "bottom",
            "showLegend": true
          },
          "tooltip": {
            "hideZeros": false,
            "mode": "single",
            "sort": "none"
          }
        },
        "pluginVersion": "11.6.0-84491.patch1-84812",
        "targets": [
          {
            "disableTextWrap": false,
            "editorMode": "builder",
            "expr": "pizza_latency_ratio",
            "fullMetaSearch": false,
            "includeNullMetadata": true,
            "legendFormat": "__auto",
            "range": true,
            "refId": "A",
            "useBackend": false
          }
        ],
        "title": "Pizza Creation Latency",
        "type": "timeseries"
      }
    ],
    "preload": false,
    "refresh": "5s",
    "schemaVersion": 41,
    "tags": [],
    "templating": {
      "list": []
    },
    "time": {
      "from": "now-5m",
      "to": "now"
    },
    "timepicker": {},
    "timezone": "browser",
    "title": "Pizza Dashboard",
    "uid": "aeg98625g0xz4e",
    "version": 30
  }